PyIpBlocker.py
__init__.py
PyIpBlocker-0.0.4.dist-info/LICENSE
PyIpBlocker-0.0.4.dist-info/METADATA
PyIpBlocker-0.0.4.dist-info/WHEEL
PyIpBlocker-0.0.4.dist-info/top_level.txt
PyIpBlocker-0.0.4.dist-info/RECORD
