Metadata-Version: 2.1
Name: PyIpBlocker
Version: 0.0.4
Summary: A small package for block and unblock ip in python
Author-email: ZachVFX <zachallrd@gmail.com>
License: MIT License
Project-URL: Homepage, https://github.com/ZachVFXX/PyIpBlocker/tree/main
Project-URL: Issues, https://github.com/ZachVFXX/PyIpBlocker/issues
Keywords: IpUtil,Ip,Block,Unblock,utility,Blocker
Classifier: Programming Language :: Python :: 3
Classifier: License :: OSI Approved :: MIT License
Classifier: Operating System :: OS Independent
Requires-Python: >=3.8
License-File: LICENSE
